psiconfig/__init__.py
psiconfig/_version.py
psiconfig/config.py
psiconfig/json_config.py
psiconfig/text.py
psiconfig/toml_config.py
psiconfig-0.0.16.dist-info/WHEEL
psiconfig-0.0.16.dist-info/METADATA
psiconfig-0.0.16.dist-info/RECORD
