Metadata-Version: 2.3
Name: psiconfig
Version: 0.0.16
Summary: A module to validate and load config files.
Author: Jeff
Author-email: Jeff <<jeffwatkins2000@gmail.com>>
Requires-Dist: iniconfig>=2.1.0
Requires-Dist: packaging>=25.0
Requires-Dist: pluggy>=1.6.0
Requires-Dist: psi-toml>=0.0.21
Requires-Dist: pygments>=2.19.2
Requires-Python: >=3.10, <3.13
